simple_dependency_injector/__init__.py
simple_dependency_injector/file_handlers.py
simple_dependency_injector/interfaces.py
simple_dependency_injector/simple_dependency_injector.py
simple_dependency_injector-0.2.0.dist-info/LICENSE
simple_dependency_injector-0.2.0.dist-info/METADATA
simple_dependency_injector-0.2.0.dist-info/WHEEL
simple_dependency_injector-0.2.0.dist-info/top_level.txt
simple_dependency_injector-0.2.0.dist-info/RECORD
