Metadata-Version: 2.1
Name: simple-dependency-injector
Version: 0.2.0
Summary: A simple dependency injection framework for Python
Home-page: https://github.com/josemanuelcarretero/python-simple-dependency-injector
Author: José Manuel Carretero
Author-email: josemanuelcarreterocuenca@gmail.com
License: UNKNOWN
Platform: UNKNOWN
Classifier: Programming Language :: Python :: 3
Classifier: License :: OSI Approved :: MIT License
Classifier: Operating System :: OS Independent
Requires-Python: >=3.6
Requires-Dist: PyYAML==6.0.2
